vds/colorizer.py
vds/config.py
vds/main.py
vds/plugins/files/f001.py
vds/plugins/files/f002.py
vds/plugins/transcription/t001.py
vds/plugins/transcription/t002.py
vds/plugins/transcription/t003.py
vds/plugins/transcription/t004.py
vds/plugins/transcription/t005.py
vds/plugins/transcription/t006.py
vds/plugins/transcription/t007.py
vds-23.3.9.dist-info/entry_points.txt
vds-23.3.9.dist-info/METADATA
vds-23.3.9.dist-info/WHEEL
vds-23.3.9.dist-info/RECORD
