Metadata-Version: 2.1
Name: vds
Version: 23.3.9
Summary: ValidDataSet - TTS Lj Speech Dataset Validator
Home-page: http://github.com/8tm/ValidDataSet
Author: Tadeusz Miszczyk
Author-email: 42252259+8tm@users.noreply.github.com
Requires-Python: >=3.8.1,<4.0
Classifier: Environment :: Console
Classifier: Intended Audience :: Developers
Classifier: Operating System :: Unix
Classifier: Programming Language :: Python :: 3
Classifier: Programming Language :: Python :: 3.9
Classifier: Programming Language :: Python :: 3.10
Classifier: Programming Language :: Python :: 3.11
Classifier: Programming Language :: Python :: 3 :: Only
Classifier: Programming Language :: Python :: 3.10
Classifier: Programming Language :: Python :: 3.11
Classifier: Programming Language :: Python :: 3.7
Classifier: Programming Language :: Python :: 3.8
Classifier: Programming Language :: Python :: 3.9
Requires-Dist: colorama (>=0.4.6,<0.5.0)
Requires-Dist: rich (>=13.3.1,<14.0.0)
Requires-Dist: tqdm (>=4.64.1,<5.0.0)
Project-URL: Documentation, https://pypi.org/project/vds
Project-URL: Repository, http://github.com/8tm/ValidDataSet
